<?xml version="1.0" encoding="UTF-8"?>
<objects serializationModel="Studio.02.02.00">
	<object class="AudioFile" id="{66ac06cc-4b67-4220-bf8f-46815d2873e3}">
		<property name="assetPath">
			<value>Music/In Game/Cosmos Defender - InGame.mp3</value>
		</property>
		<property name="isStreaming">
			<value>true</value>
		</property>
		<property name="frequencyInKHz">
			<value>44.0999985</value>
		</property>
		<property name="channelCount">
			<value>2</value>
		</property>
		<property name="length">
			<value>94.85061224489796</value>
		</property>
		<relationship name="masterAssetFolder">
			<destination>{ba82e999-11c9-4353-8cee-d532737f7def}</destination>
		</relationship>
	</object>
</objects>
